tempmail_cli.py
tempmail_cli-2025.5.8.dist-info/METADATA
tempmail_cli-2025.5.8.dist-info/WHEEL
tempmail_cli-2025.5.8.dist-info/entry_points.txt
tempmail_cli-2025.5.8.dist-info/top_level.txt
tempmail_cli-2025.5.8.dist-info/RECORD
